README.rst
setup.py
anoikis/__init__.py
anoikis/exceptions.py
anoikis/helpers.py
anoikis.egg-info/PKG-INFO
anoikis.egg-info/SOURCES.txt
anoikis.egg-info/dependency_links.txt
anoikis.egg-info/entry_points.txt
anoikis.egg-info/requires.txt
anoikis.egg-info/top_level.txt