Metadata-Version: 1.0
Name: anoikis
Version: 0.1
Summary: Python library for common EVE Online tasks
Home-page: https://github.com/ikanobori
Author: Simon de Vlieger
Author-email: simon@ikanobori.jp
License: UNKNOWN
Platform: UNKNOWN
